{
  "$schema": "https://json.schemastore.org/tsconfig",
  "display": "Default",
  "compilerOptions": {
    "allowJs": true,
    "declaration": false,
    "declarationMap": false,
    "skipLibCheck": true,
    "incremental": true,
    "jsx": "preserve",
    "forceConsistentCasingInFileNames": true,
    "lib": ["dom", "dom.iterable", "esnext", "es5", "es6"],
    "module": "esnext",
    "noEmit": true,
    "moduleResolution": "node",
    "esModuleInterop": true,
    "resolveJsonModule": true,
    "isolatedModules": true,
    "strict": true,
    "target": "es6",
    "paths": {
      "@/*": ["./src/*"]
    },
    "plugins": [
      {
        "name": "next"
      }
    ]
  },
  "include": ["next-env.d.ts", "**/*.ts", "**/*.tsx", ".next/types/**/*.ts"],
  "exclude": ["node_modules"]
}
